naqsh/__init__.py
naqsh-0.1.0.dist-info/METADATA
naqsh-0.1.0.dist-info/WHEEL
naqsh-0.1.0.dist-info/top_level.txt
naqsh-0.1.0.dist-info/RECORD
