Metadata-Version: 2.1
Name: naqsh
Version: 0.1.0
Summary: Naqsh
Author-email: alMukaafih <almukaafih@gmail.com>
Classifier: Programming Language :: Python :: 3
Classifier: License :: OSI Approved :: Apache Software License
Classifier: Operating System :: OS Independent
Requires-Python: >=3.8
